fonderlib/__init__.py
fonderlib/common/__init__.py
fonderlib/common/error.py
fonderlib/common/fonder_error.py
fonderlib/common/logger.py
fonderlib/common/parser.py
fonderlib/config/__init__.py
fonderlib/config/config_service.py
fonderlib/config/keys.py
fonderlib/config/secret_manager.py
fonderlib/db/__init__.py
fonderlib/db/db_service.py
fonderlib/loaders/__init__.py
fonderlib/loaders/csv_loader.py
fonderlib/loaders/loader.py
fonderlib/loaders/pdf_loader.py
fonderlib/pandas/__init__.py
fonderlib/pandas/pandas_service.py
fonderlib/pipelines/__init__.py
fonderlib/pipelines/context.py
fonderlib/pipelines/pipeline_manager.py
fonderlib/scripts/README.md
fonderlib/scripts/__init__.py
fonderlib/scripts/config_usage.py
fonderlib/scripts/errors_usage.py
fonderlib/scripts/logging_usage.py
fonderlib/scripts/parser_usage.py
fonderlib/services/__init__.py
fonderlib/services/tenant_service.py
fonderlib/tasks/__init__.py
fonderlib/tasks/task.py
fonderlib/tasks/task_result.py
fonderlib/utils/__init__.py
fonderlib/utils/date.py
fonderlib/utils/json.py
fonderlib/utils/pagination.py
fonderlib/utils/print.py
fonderlib/utils/utils.py
fonderlib-1.0.35.dist-info/METADATA
fonderlib-1.0.35.dist-info/WHEEL
fonderlib-1.0.35.dist-info/RECORD
